sphinx_git/__init__.py
sphinx_git/version.py
sphinx_git-10.1.1.dist-info/DESCRIPTION.rst
sphinx_git-10.1.1.dist-info/METADATA
sphinx_git-10.1.1.dist-info/RECORD
sphinx_git-10.1.1.dist-info/WHEEL
sphinx_git-10.1.1.dist-info/metadata.json
sphinx_git-10.1.1.dist-info/top_level.txt
