Metadata-Version: 2.0
Name: sphinx-git
Version: 10.1.1
Summary: git Changelog for Sphinx
Home-page: https://github.com/OddBloke/sphinx-git
Author: Daniel Watkins
Author-email: daniel@daniel-watkins.co.uk
License: UNKNOWN
Platform: UNKNOWN
Requires-Dist: six
Requires-Dist: sphinx
Requires-Dist: GitPython (>=0.3.6)
